TracPrivateTickets-2.3.0.dist-info/METADATA
TracPrivateTickets-2.3.0.dist-info/RECORD
TracPrivateTickets-2.3.0.dist-info/WHEEL
TracPrivateTickets-2.3.0.dist-info/entry_points.txt
TracPrivateTickets-2.3.0.dist-info/top_level.txt
privatetickets/__init__.py
privatetickets/policy.py
