Metadata-Version: 2.1
Name: TracPrivateTickets
Version: 2.3.0
Summary: Modified ticket security for Trac.
Home-page: https://trac-hacks.org/wiki/PrivateTicketsPlugin
Author: Noah Kantrowitz
Author-email: noah@coderanger.net
Maintainer: Ryan J Ollos
Maintainer-email: ryan.j.ollos@gmail.com
License: BSD 3-Clause
Keywords: trac plugin ticket permissions security
Platform: UNKNOWN
Classifier: Framework :: Trac
Requires-Dist: Trac
